[{"CandidateName":"आरेन राई","Gender":"पुरुष","Age":29,"PartyID":0,"SymbolID":2501,"SymbolName":"अँजुलीमा रहेको माटो","CandidateID":339964,"StateName":"कोशी प्रदेश","PoliticalPartyName":"श्रम संस्कृति पार्टी","ElectionPost":null,"DistrictCd":12,"DistrictName":"खोटाङ","State":1,"SCConstID":"1","CenterConstID":null,"SerialNo":435,"TotalVoteReceived":1474,"CastedVote":0,"TotalVoters":0,"Rank":"1","Remarks":null,"Samudaya":null,"DOB":"2053-06-08","CTZDIST":"खोटाङ","FATHER_NAME":"एकराज  राई","SPOUCE_NAME":"प्रमिला  राई","QUALIFICATION":"+2","EXPERIENCE":"विगत  निकै लामो समय देखि राजनीतिक समाजिक क्षेत्रमा काम गर्दै आएको । समाज देखिएको विभिन्न मुद्दाहरुको लागि काम गर्दै आएको । ","OTHERDETAILS":"","NAMEOFINST":"कितिनी कलेज ललितपुर","ADDRESS":"खोटाङ केपिलासगढी गाउँपालिका "},{"CandidateName":"वीर काजी राई","Gender":"पुरुष","Age":51,"PartyID":0,"SymbolID":2583,"SymbolName":"रुख","CandidateID":341644,"StateName":"कोशी प्रदेश","PoliticalPartyName":"नेपाली काँग्रेस","ElectionPost":null,"DistrictCd":12,"DistrictName":"खोटाङ","State":1,"SCConstID":"1","CenterConstID":null,"SerialNo":436,"TotalVoteReceived":876,"CastedVote":0,"TotalVoters":0,"Rank":"1","Remarks":null,"Samudaya":null,"DOB":"2031-01-15","CTZDIST":"खोटाङ","FATHER_NAME":"दल बहादुर राई","SPOUCE_NAME":"विष्णु  राई","QUALIFICATION":"","EXPERIENCE":"","OTHERDETAILS":"","NAMEOFINST":"","ADDRESS":"खोटाङ केपिलासगढी गाउँपालिका फेदीटोल"},{"CandidateName":"हरि रोका","Gender":"पुरुष","Age":67,"PartyID":0,"SymbolID":2557,"SymbolName":"पाँचकुने तारा","CandidateID":340262,"StateName":"कोशी प्रदेश","PoliticalPartyName":"नेपाली कम्युनिष्ट पार्टी","ElectionPost":null,"DistrictCd":12,"DistrictName":"खोटाङ","State":1,"SCConstID":"1","CenterConstID":null,"SerialNo":437,"TotalVoteReceived":491,"CastedVote":0,"TotalVoters":0,"Rank":"1","Remarks":null,"Samudaya":null,"DOB":"2015-06-15","CTZDIST":"खोटाङ","FATHER_NAME":"मेग बहादुर रोका","SPOUCE_NAME":"कृष्णा  रोका","QUALIFICATION":"विधावारिधि","EXPERIENCE":"जिल्ला इन्चार्ज जिल्ला सचिव केन्द्रिय समिती\nस.सचिव सहकारी विकास बोर्ड\nप्रतिनिधि सभा सदस्य अन्तरिम प्रतिनिधि 2063\nसंविधान सभा संस्करण लेखक","OTHERDETAILS":"मुलुको आर्थिक सामाजिक रुपान्तरणको आवश्यकता लाई सबैले संवोधन गर्ने आवश्यक छ।","NAMEOFINST":"जवाराहाल नेहरु विश्वाविधालय नयाँ दिल्ली","ADDRESS":"खोटाङ दिप्रुङ चुइचुम्मा गाउँपालिका खुतुम्बु"},{"CandidateName":"देव विक्रम राई","Gender":"पुरुष","Age":56,"PartyID":0,"SymbolID":2598,"SymbolName":"सुर्य","CandidateID":340043,"StateName":"कोशी प्रदेश","PoliticalPartyName":"नेपाल कम्युनिष्ट पार्टी (एकीकृत मार्क्सवादी लेनिनवादी)","ElectionPost":null,"DistrictCd":12,"DistrictName":"खोटाङ","State":1,"SCConstID":"1","CenterConstID":null,"SerialNo":438,"TotalVoteReceived":439,"CastedVote":0,"TotalVoters":0,"Rank":"1","Remarks":null,"Samudaya":null,"DOB":"2026-03-22","CTZDIST":"खोटाङ","FATHER_NAME":"शुभ सेर राई","SPOUCE_NAME":"निर्मला  राई","QUALIFICATION":"एम‍.ए. (स्नातकोत्तर)","EXPERIENCE":"","OTHERDETAILS":"","NAMEOFINST":"त्रिभुवन विश्व विद्यालय","ADDRESS":"खोटाङ दिक्तेल रुपाकोट मझुवागढी नगरपालिका छिप्ती"},{"CandidateName":"रुद्र गिरी","Gender":"पुरुष","Age":54,"PartyID":0,"SymbolID":2528,"SymbolName":"घण्टी","CandidateID":340918,"StateName":"कोशी प्रदेश","PoliticalPartyName":"राष्ट्रिय स्वतन्त्र पार्टी","ElectionPost":null,"DistrictCd":12,"DistrictName":"खोटाङ","State":1,"SCConstID":"1","CenterConstID":null,"SerialNo":439,"TotalVoteReceived":112,"CastedVote":0,"TotalVoters":0,"Rank":"1","Remarks":null,"Samudaya":null,"DOB":"2028-08-24","CTZDIST":"खोटाङ","FATHER_NAME":"रत्‍न  गिरी","SPOUCE_NAME":"सरस्वती  गिरी","QUALIFICATION":"प्रमाण पत्र तह","EXPERIENCE":"नेपाली नेत्रज्योति संघ खोटाङ पूर्वसभापति\nखोटाङ उधोग वाणिज्य संघ पूर्व अध्यक्ष\nहोटल हलेसी भिलेज संचालक","OTHERDETAILS":"","NAMEOFINST":"दिक्तेल बहुमुखि क्याम्पस","ADDRESS":"खोटाङ दिक्तेल रुपाकोट मझुवागढी नगरपालिका "},{"CandidateName":"मिरेश राई","Gender":"पुरुष","Age":25,"PartyID":0,"SymbolID":2568,"SymbolName":"बाँसुरी","CandidateID":341217,"StateName":"कोशी प्रदेश","PoliticalPartyName":"राष्ट्रिय परिवर्तन पार्टी","ElectionPost":null,"DistrictCd":12,"DistrictName":"खोटाङ","State":1,"SCConstID":"1","CenterConstID":null,"SerialNo":440,"TotalVoteReceived":55,"CastedVote":0,"TotalVoters":0,"Rank":"1","Remarks":null,"Samudaya":null,"DOB":"2057-08-01","CTZDIST":"खोटाङ","FATHER_NAME":"गम राज राई","SPOUCE_NAME":"-","QUALIFICATION":"बि.एड","EXPERIENCE":"","OTHERDETAILS":"","NAMEOFINST":"महेन्द्र रत्न क्याम्पस ताहचल","ADDRESS":"खोटाङ हलेसी तुवाचुङ नगरपालिका छापडाँड"},{"CandidateName":"राकेश राई","Gender":"पुरुष","Age":60,"PartyID":0,"SymbolID":2531,"SymbolName":"चकिया (जाँतो)","CandidateID":340862,"StateName":"कोशी प्रदेश","PoliticalPartyName":"जनता समाजवादी पार्टी(एकल चुनाव चिन्ह)","ElectionPost":null,"DistrictCd":12,"DistrictName":"खोटाङ","State":1,"SCConstID":"1","CenterConstID":null,"SerialNo":441,"TotalVoteReceived":21,"CastedVote":0,"TotalVoters":0,"Rank":"1","Remarks":null,"Samudaya":null,"DOB":"2022-01-14","CTZDIST":"खोटाङ","FATHER_NAME":"रत्न  राई","SPOUCE_NAME":"अञ्जना कुमारी राई","QUALIFICATION":"एस.एल.सी","EXPERIENCE":"","OTHERDETAILS":"","NAMEOFINST":"चम्मावति मा.वि बईपा","ADDRESS":"खोटाङ दिक्तेल रुपाकोट मझुवागढी नगरपालिका "},{"CandidateName":"दिपक तामाङ्ग","Gender":"पुरुष","Age":43,"PartyID":0,"SymbolID":2604,"SymbolName":"हलो","CandidateID":341376,"StateName":"कोशी प्रदेश","PoliticalPartyName":"राष्ट्रिय प्रजातन्त्र पार्टी","ElectionPost":null,"DistrictCd":12,"DistrictName":"खोटाङ","State":1,"SCConstID":"1","CenterConstID":null,"SerialNo":442,"TotalVoteReceived":10,"CastedVote":0,"TotalVoters":0,"Rank":"1","Remarks":null,"Samudaya":null,"DOB":"2039-11-12","CTZDIST":"खोटाङ","FATHER_NAME":"ईश्‍वर बहादुर तामाङ्ग","SPOUCE_NAME":"खिला  मगर (तामाङ्ग)","QUALIFICATION":"","EXPERIENCE":"नेपाली सेनामा १६ वर्ष १३ दिन  सेवा गरेको","OTHERDETAILS":"सुशासन कायम गर्न","NAMEOFINST":"","ADDRESS":"खोटाङ हलेसी तुवाचुङ नगरपालिका बाङ्गामा"},{"CandidateName":"सुनिल चाम्लिङ","Gender":"पुरुष","Age":40,"PartyID":0,"SymbolID":2542,"SymbolName":"ढल्केको छाता","CandidateID":340364,"StateName":"कोशी प्रदेश","PoliticalPartyName":"जनता समाजवादी पार्टी, नेपाल","ElectionPost":null,"DistrictCd":12,"DistrictName":"खोटाङ","State":1,"SCConstID":"1","CenterConstID":null,"SerialNo":443,"TotalVoteReceived":6,"CastedVote":0,"TotalVoters":0,"Rank":"1","Remarks":null,"Samudaya":null,"DOB":"2042-01-15","CTZDIST":"खोटाङ","FATHER_NAME":"निर बहादुर राई","SPOUCE_NAME":"सरला  राई","QUALIFICATION":"एस.एल.सी","EXPERIENCE":"","OTHERDETAILS":"","NAMEOFINST":"श्री मा.वि. मझुवा बास्बोटे","ADDRESS":"खोटाङ दिक्तेल रुपाकोट मझुवागढी नगरपालिका "},{"CandidateName":"चन्द्र बहादुर बुढाथोकी","Gender":"पुरुष","Age":47,"PartyID":0,"SymbolID":2526,"SymbolName":"गोलो घेराभित्र दुई पात भएको गुलाफको फूल","CandidateID":340424,"StateName":"कोशी प्रदेश","PoliticalPartyName":"नेपाल कम्युनिस्ट पार्टी (माओवादी)","ElectionPost":null,"DistrictCd":12,"DistrictName":"खोटाङ","State":1,"SCConstID":"1","CenterConstID":null,"SerialNo":444,"TotalVoteReceived":4,"CastedVote":0,"TotalVoters":0,"Rank":"1","Remarks":null,"Samudaya":null,"DOB":"2035-04-12","CTZDIST":"खोटाङ","FATHER_NAME":"बखत बहादुर बुढाथोकी","SPOUCE_NAME":"राधा  बुढाथोकी","QUALIFICATION":"स्नातक तह","EXPERIENCE":"","OTHERDETAILS":"","NAMEOFINST":"त्रि.वि.वि(भोजपुर बहुमुखी क्याम्पस भोजपुर)","ADDRESS":"खोटाङ साकेला गाउँपालिका सेखुवा"},{"CandidateName":"ध्यान प्रसाद ढकाल","Gender":"पुरुष","Age":53,"PartyID":0,"SymbolID":2578,"SymbolName":"मादल","CandidateID":339609,"StateName":"कोशी प्रदेश","PoliticalPartyName":"नेपाल मजदुर किसान पार्टी","ElectionPost":null,"DistrictCd":12,"DistrictName":"खोटाङ","State":1,"SCConstID":"1","CenterConstID":null,"SerialNo":445,"TotalVoteReceived":2,"CastedVote":0,"TotalVoters":0,"Rank":"1","Remarks":null,"Samudaya":null,"DOB":"2029.03.14","CTZDIST":"खोटाङ","FATHER_NAME":"श्रीलाल पाध्या ढकाल","SPOUCE_NAME":"-","QUALIFICATION":"एस.एल.सि.","EXPERIENCE":"","OTHERDETAILS":"देश जनताको सेवा गर्ने","NAMEOFINST":"सरस्वती मा.वि. मात्तिम","ADDRESS":"खोटाङ साकेला गाउँपालिका "},{"CandidateName":"केशर मान चाम्लिङ","Gender":"पुरुष","Age":47,"PartyID":0,"SymbolID":2530,"SymbolName":"घोडा","CandidateID":341463,"StateName":"कोशी प्रदेश","PoliticalPartyName":"मितेरी पार्टी नेपाल","ElectionPost":null,"DistrictCd":12,"DistrictName":"खोटाङ","State":1,"SCConstID":"1","CenterConstID":null,"SerialNo":446,"TotalVoteReceived":2,"CastedVote":0,"TotalVoters":0,"Rank":"1","Remarks":null,"Samudaya":null,"DOB":"2035-04-09","CTZDIST":"खोटाङ","FATHER_NAME":"मुगाधन  राई","SPOUCE_NAME":"प्रभा  राई","QUALIFICATION":"एस.एल.सि.","EXPERIENCE":"","OTHERDETAILS":"","NAMEOFINST":"","ADDRESS":"खोटाङ दिक्तेल रुपाकोट मझुवागढी नगरपालिका "},{"CandidateName":"तिलक चन्द्र राई","Gender":"पुरुष","Age":42,"PartyID":0,"SymbolID":2620,"SymbolName":"कैंची","CandidateID":341259,"StateName":"कोशी प्रदेश","PoliticalPartyName":"स्वतन्त्र","ElectionPost":null,"DistrictCd":12,"DistrictName":"खोटाङ","State":1,"SCConstID":"1","CenterConstID":null,"SerialNo":447,"TotalVoteReceived":2,"CastedVote":0,"TotalVoters":0,"Rank":"1","Remarks":null,"Samudaya":null,"DOB":"2040-11-13","CTZDIST":"खोटाङ","FATHER_NAME":"विश्वराज  राई","SPOUCE_NAME":"-","QUALIFICATION":"एस.एल.सी","EXPERIENCE":"","OTHERDETAILS":"","NAMEOFINST":"","ADDRESS":"खोटाङ दिप्रुङ चुइचुम्मा गाउँपालिका टेम्मा"},{"CandidateName":"प्रयाग राई","Gender":"पुरुष","Age":35,"PartyID":0,"SymbolID":2511,"SymbolName":"कुखुराको भाले","CandidateID":340584,"StateName":"कोशी प्रदेश","PoliticalPartyName":"मंगोल नेशनल अर्गनाइजेसन","ElectionPost":null,"DistrictCd":12,"DistrictName":"खोटाङ","State":1,"SCConstID":"1","CenterConstID":null,"SerialNo":448,"TotalVoteReceived":1,"CastedVote":0,"TotalVoters":0,"Rank":"1","Remarks":null,"Samudaya":null,"DOB":"2047-06-17","CTZDIST":"खोटाङ","FATHER_NAME":"बाल कुमार राई","SPOUCE_NAME":"यसोदा  कन्दङवा","QUALIFICATION":"माध्यमिक तह","EXPERIENCE":"","OTHERDETAILS":"","NAMEOFINST":"श्री सबित्रा माध्यमिक विधालय","ADDRESS":"खोटाङ दिक्तेल रुपाकोट मझुवागढी नगरपालिका "},{"CandidateName":"राज कुमार राई","Gender":"पुरुष","Age":63,"PartyID":0,"SymbolID":2670,"SymbolName":"मुढा","CandidateID":341731,"StateName":"कोशी प्रदेश","PoliticalPartyName":"स्वतन्त्र","ElectionPost":null,"DistrictCd":12,"DistrictName":"खोटाङ","State":1,"SCConstID":"1","CenterConstID":null,"SerialNo":449,"TotalVoteReceived":1,"CastedVote":0,"TotalVoters":0,"Rank":"1","Remarks":null,"Samudaya":null,"DOB":"2019-04-05","CTZDIST":"झापा","FATHER_NAME":"पंच बहादुर राई","SPOUCE_NAME":"प्यारो  राई","QUALIFICATION":"पि.एच.डि.","EXPERIENCE":"शिक्षण प्राध्यापन ३० वर्ष भन्दा माथी","OTHERDETAILS":"अध्ययन अनुसन्धान तथा लेखन कार्यमा रुची\nसमाज सेवा प्रति ","NAMEOFINST":"The University of Tenessee Knoxville USA","ADDRESS":"खोटाङ रावा बेसी गाउँपालिका "}]