[
  {
    "CandidateName": "सोविता गौतम",
    "Gender": "महिला",
    "Age": 30,
    "PartyID": 0,
    "SymbolID": 2528,
    "SymbolName": "घण्टी",
    "CandidateID": 341145,
    "StateName": "बागमती प्रदेश",
    "PoliticalPartyName": "राष्ट्रिय स्वतन्त्र पार्टी",
    "ElectionPost": null,
    "DistrictCd": 35,
    "DistrictName": "चितवन",
    "State": 3,
    "SCConstID": "3",
    "CenterConstID": null,
    "SerialNo": 2231,
    "TotalVoteReceived": 19319,
    "CastedVote": 0,
    "TotalVoters": 0,
    "Rank": "1",
    "Remarks": null,
    "Samudaya": null,
    "DOB": "2052-03-03",
    "CTZDIST": "दोलखा",
    "FATHER_NAME": "कृष्ण प्रसाद गौतम",
    "SPOUCE_NAME": "गृहेन्द्र घिमिरे",
    "QUALIFICATION": "स्नातकोत्तर (कानून)",
    "EXPERIENCE": "",
    "OTHERDETAILS": "",
    "NAMEOFINST": "",
    "ADDRESS": "चितवन भरतपुर महानगरपालिका "
  },
  {
    "CandidateName": "रेणु दाहाल",
    "Gender": "महिला",
    "Age": 49,
    "PartyID": 0,
    "SymbolID": 2557,
    "SymbolName": "पाँचकुने तारा",
    "CandidateID": 339835,
    "StateName": "बागमती प्रदेश",
    "PoliticalPartyName": "नेपाली कम्युनिष्ट पार्टी",
    "ElectionPost": null,
    "DistrictCd": 35,
    "DistrictName": "चितवन",
    "State": 3,
    "SCConstID": "3",
    "CenterConstID": null,
    "SerialNo": 2232,
    "TotalVoteReceived": 8539,
    "CastedVote": 0,
    "TotalVoters": 0,
    "Rank": "1",
    "Remarks": null,
    "Samudaya": null,
    "DOB": "2033-03-23",
    "CTZDIST": "चितवन",
    "FATHER_NAME": "पुष्‍प कमल दाहाल",
    "SPOUCE_NAME": "अनिल कुमार पाठक",
    "QUALIFICATION": "",
    "EXPERIENCE": "",
    "OTHERDETAILS": "",
    "NAMEOFINST": "",
    "ADDRESS": "चितवन भरतपुर महानगरपालिका "
  },
  {
    "CandidateName": "टेक प्रसाद गुरुङ्ग",
    "Gender": "पुरुष",
    "Age": 77,
    "PartyID": 0,
    "SymbolID": 2583,
    "SymbolName": "रुख",
    "CandidateID": 340483,
    "StateName": "बागमती प्रदेश",
    "PoliticalPartyName": "नेपाली काँग्रेस",
    "ElectionPost": null,
    "DistrictCd": 35,
    "DistrictName": "चितवन",
    "State": 3,
    "SCConstID": "3",
    "CenterConstID": null,
    "SerialNo": 2233,
    "TotalVoteReceived": 2343,
    "CastedVote": 0,
    "TotalVoters": 0,
    "Rank": "1",
    "Remarks": null,
    "Samudaya": null,
    "DOB": "2005-09-16",
    "CTZDIST": "चितवन",
    "FATHER_NAME": "डम्बर सिं गुरुङ्ग",
    "SPOUCE_NAME": "शिर माया गुरुङ्ग",
    "QUALIFICATION": "SLC",
    "EXPERIENCE": "",
    "OTHERDETAILS": "",
    "NAMEOFINST": "",
    "ADDRESS": "चितवन भरतपुर महानगरपालिका सूर्यनगर"
  },
  {
    "CandidateName": "शंकर राज थपलिया",
    "Gender": "पुरुष",
    "Age": 56,
    "PartyID": 0,
    "SymbolID": 2598,
    "SymbolName": "सुर्य",
    "CandidateID": 340259,
    "StateName": "बागमती प्रदेश",
    "PoliticalPartyName": "नेपाल कम्युनिष्ट पार्टी (एकीकृत मार्क्सवादी लेनिनवादी)",
    "ElectionPost": null,
    "DistrictCd": 35,
    "DistrictName": "चितवन",
    "State": 3,
    "SCConstID": "3",
    "CenterConstID": null,
    "SerialNo": 2234,
    "TotalVoteReceived": 2138,
    "CastedVote": 0,
    "TotalVoters": 0,
    "Rank": "1",
    "Remarks": null,
    "Samudaya": null,
    "DOB": "2026-05-29",
    "CTZDIST": "चितवन",
    "FATHER_NAME": "मधुसुदन  थपलिया",
    "SPOUCE_NAME": "यमुना  थपलिया",
    "QUALIFICATION": "",
    "EXPERIENCE": "",
    "OTHERDETAILS": "",
    "NAMEOFINST": "",
    "ADDRESS": "चितवन भरतपुर महानगरपालिका धनौजी"
  },
  {
    "CandidateName": "दिपक थापा (मगर)",
    "Gender": "पुरुष",
    "Age": 47,
    "PartyID": 0,
    "SymbolID": 2604,
    "SymbolName": "हलो",
    "CandidateID": 339936,
    "StateName": "बागमती प्रदेश",
    "PoliticalPartyName": "राष्ट्रिय प्रजातन्त्र पार्टी",
    "ElectionPost": null,
    "DistrictCd": 35,
    "DistrictName": "चितवन",
    "State": 3,
    "SCConstID": "3",
    "CenterConstID": null,
    "SerialNo": 2235,
    "TotalVoteReceived": 470,
    "CastedVote": 0,
    "TotalVoters": 0,
    "Rank": "1",
    "Remarks": null,
    "Samudaya": null,
    "DOB": "2035-07-26",
    "CTZDIST": "चितवन",
    "FATHER_NAME": "तिलक बहादुर थापा (मगर)",
    "SPOUCE_NAME": "नीतु  थापा (मगर)",
    "QUALIFICATION": "स्नातक",
    "EXPERIENCE": "",
    "OTHERDETAILS": "",
    "NAMEOFINST": "",
    "ADDRESS": "चितवन भरतपुर महानगरपालिका धर्मपुर"
  },
  {
    "CandidateName": "तोजमान गुरुङ्ग",
    "Gender": "पुरुष",
    "Age": 38,
    "PartyID": 0,
    "SymbolID": 2501,
    "SymbolName": "अँजुलीमा रहेको माटो",
    "CandidateID": 339575,
    "StateName": "बागमती प्रदेश",
    "PoliticalPartyName": "श्रम संस्कृति पार्टी",
    "ElectionPost": null,
    "DistrictCd": 35,
    "DistrictName": "चितवन",
    "State": 3,
    "SCConstID": "3",
    "CenterConstID": null,
    "SerialNo": 2236,
    "TotalVoteReceived": 149,
    "CastedVote": 0,
    "TotalVoters": 0,
    "Rank": "1",
    "Remarks": null,
    "Samudaya": null,
    "DOB": "2043-12-16",
    "CTZDIST": "चितवन",
    "FATHER_NAME": "दुर्गा बहादुर गुरुङ्ग",
    "SPOUCE_NAME": "-",
    "QUALIFICATION": "SLC",
    "EXPERIENCE": "",
    "OTHERDETAILS": "",
    "NAMEOFINST": "",
    "ADDRESS": "चितवन माडी नगरपालिका "
  },
  {
    "CandidateName": "इन्द्र माया पौडेल",
    "Gender": "महिला",
    "Age": 58,
    "PartyID": 0,
    "SymbolID": 2630,
    "SymbolName": "चेसगोटी",
    "CandidateID": 339304,
    "StateName": "बागमती प्रदेश",
    "PoliticalPartyName": "स्वतन्त्र",
    "ElectionPost": null,
    "DistrictCd": 35,
    "DistrictName": "चितवन",
    "State": 3,
    "SCConstID": "3",
    "CenterConstID": null,
    "SerialNo": 2237,
    "TotalVoteReceived": 132,
    "CastedVote": 0,
    "TotalVoters": 0,
    "Rank": "1",
    "Remarks": null,
    "Samudaya": null,
    "DOB": "2023-12-29",
    "CTZDIST": "चितवन",
    "FATHER_NAME": "बुद्धि सागर पौडेल",
    "SPOUCE_NAME": "कृष्ण राज न्यौपाने",
    "QUALIFICATION": "स्नातक तह",
    "EXPERIENCE": "",
    "OTHERDETAILS": "",
    "NAMEOFINST": "विरेन्द्र बहुमुखी कलेज",
    "ADDRESS": "चितवन भरतपुर महानगरपालिका दिपेन्द्र नगर"
  },
  {
    "CandidateName": "आशिक प्रसाद महतो",
    "Gender": "पुरुष",
    "Age": 36,
    "PartyID": 0,
    "SymbolID": 2526,
    "SymbolName": "गोलो घेराभित्र दुई पात भएको गुलाफको फूल",
    "CandidateID": 340775,
    "StateName": "बागमती प्रदेश",
    "PoliticalPartyName": "नेपाल कम्युनिस्ट पार्टी (माओवादी)",
    "ElectionPost": null,
    "DistrictCd": 35,
    "DistrictName": "चितवन",
    "State": 3,
    "SCConstID": "3",
    "CenterConstID": null,
    "SerialNo": 2238,
    "TotalVoteReceived": 67,
    "CastedVote": 0,
    "TotalVoters": 0,
    "Rank": "1",
    "Remarks": null,
    "Samudaya": null,
    "DOB": "2046-06-20",
    "CTZDIST": "चितवन",
    "FATHER_NAME": "गोरिया प्रसाद महतो",
    "SPOUCE_NAME": "-",
    "QUALIFICATION": "स्नातक",
    "EXPERIENCE": "",
    "OTHERDETAILS": "",
    "NAMEOFINST": "",
    "ADDRESS": "चितवन माडी नगरपालिका खैरहनी"
  },
  {
    "CandidateName": "डम्बर बहादुर तमाङ",
    "Gender": "पुरुष",
    "Age": 50,
    "PartyID": 0,
    "SymbolID": 2566,
    "SymbolName": "बलिरहेको बिजुलीको चिम",
    "CandidateID": 341085,
    "StateName": "बागमती प्रदेश",
    "PoliticalPartyName": "उज्यालो नेपाल पार्टी",
    "ElectionPost": null,
    "DistrictCd": 35,
    "DistrictName": "चितवन",
    "State": 3,
    "SCConstID": "3",
    "CenterConstID": null,
    "SerialNo": 2239,
    "TotalVoteReceived": 60,
    "CastedVote": 0,
    "TotalVoters": 0,
    "Rank": "1",
    "Remarks": null,
    "Samudaya": null,
    "DOB": "2032-01-05",
    "CTZDIST": "चितवन",
    "FATHER_NAME": "सिंगे  तमाङ",
    "SPOUCE_NAME": "जुना  तमाङ",
    "QUALIFICATION": "SLC",
    "EXPERIENCE": "",
    "OTHERDETAILS": "",
    "NAMEOFINST": "",
    "ADDRESS": "चितवन भरतपुर महानगरपालिका चन्द्रनगर"
  },
  {
    "CandidateName": "बुध्दी राज तमाङ",
    "Gender": "पुरुष",
    "Age": 43,
    "PartyID": 0,
    "SymbolID": 2516,
    "SymbolName": "खुलेको एकल आँखा",
    "CandidateID": 341817,
    "StateName": "बागमती प्रदेश",
    "PoliticalPartyName": "प्रगतिशील लोकतान्त्रिक पार्टी",
    "ElectionPost": null,
    "DistrictCd": 35,
    "DistrictName": "चितवन",
    "State": 3,
    "SCConstID": "3",
    "CenterConstID": null,
    "SerialNo": 2240,
    "TotalVoteReceived": 44,
    "CastedVote": 0,
    "TotalVoters": 0,
    "Rank": "1",
    "Remarks": null,
    "Samudaya": null,
    "DOB": "2039-08-24",
    "CTZDIST": "चितवन",
    "FATHER_NAME": "रणबिर  तमाङ",
    "SPOUCE_NAME": "जमुना  लामा",
    "QUALIFICATION": "+2",
    "EXPERIENCE": "",
    "OTHERDETAILS": "",
    "NAMEOFINST": "",
    "ADDRESS": "चितवन भरतपुर महानगरपालिका "
  },
  {
    "CandidateName": "रञ्जना पौडेल",
    "Gender": "महिला",
    "Age": 45,
    "PartyID": 0,
    "SymbolID": 2640,
    "SymbolName": "ट्रफी",
    "CandidateID": 341878,
    "StateName": "बागमती प्रदेश",
    "PoliticalPartyName": "स्वतन्त्र",
    "ElectionPost": null,
    "DistrictCd": 35,
    "DistrictName": "चितवन",
    "State": 3,
    "SCConstID": "3",
    "CenterConstID": null,
    "SerialNo": 2241,
    "TotalVoteReceived": 33,
    "CastedVote": 0,
    "TotalVoters": 0,
    "Rank": "1",
    "Remarks": null,
    "Samudaya": null,
    "DOB": "2037-02-27",
    "CTZDIST": "चितवन",
    "FATHER_NAME": "दया निधि रेग्मी",
    "SPOUCE_NAME": "गणेश पौडेल",
    "QUALIFICATION": "",
    "EXPERIENCE": "",
    "OTHERDETAILS": "",
    "NAMEOFINST": "",
    "ADDRESS": "चितवन भरतपुर महानगरपालिका हिमाली पथ"
  },
  {
    "CandidateName": "टेक बहादुर तामाङ",
    "Gender": "पुरुष",
    "Age": 50,
    "PartyID": 0,
    "SymbolID": 2511,
    "SymbolName": "कुखुराको भाले",
    "CandidateID": 339615,
    "StateName": "बागमती प्रदेश",
    "PoliticalPartyName": "मंगोल नेशनल अर्गनाइजेसन",
    "ElectionPost": null,
    "DistrictCd": 35,
    "DistrictName": "चितवन",
    "State": 3,
    "SCConstID": "3",
    "CenterConstID": null,
    "SerialNo": 2242,
    "TotalVoteReceived": 14,
    "CastedVote": 0,
    "TotalVoters": 0,
    "Rank": "1",
    "Remarks": null,
    "Samudaya": null,
    "DOB": "2032-02-12",
    "CTZDIST": "चितवन",
    "FATHER_NAME": "मान बहादुर तामाङ",
    "SPOUCE_NAME": "शुष्मा  तामाङ",
    "QUALIFICATION": "SLC",
    "EXPERIENCE": "",
    "OTHERDETAILS": "",
    "NAMEOFINST": "",
    "ADDRESS": "चितवन भरतपुर महानगरपालिका गोरखाली टोल"
  },
  {
    "CandidateName": "जित बहादुर बि.क.",
    "Gender": "पुरुष",
    "Age": 48,
    "PartyID": 0,
    "SymbolID": 2601,
    "SymbolName": "हँसिया",
    "CandidateID": 342041,
    "StateName": "बागमती प्रदेश",
    "PoliticalPartyName": "नेपाल कम्युनिष्ट पार्टी (संयुक्त)",
    "ElectionPost": null,
    "DistrictCd": 35,
    "DistrictName": "चितवन",
    "State": 3,
    "SCConstID": "3",
    "CenterConstID": null,
    "SerialNo": 2243,
    "TotalVoteReceived": 13,
    "CastedVote": 0,
    "TotalVoters": 0,
    "Rank": "1",
    "Remarks": null,
    "Samudaya": null,
    "DOB": "2034-11-12",
    "CTZDIST": "चितवन",
    "FATHER_NAME": "नर बहादुर बि.क.",
    "SPOUCE_NAME": "-",
    "QUALIFICATION": "",
    "EXPERIENCE": "",
    "OTHERDETAILS": "",
    "NAMEOFINST": "",
    "ADDRESS": "चितवन भरतपुर महानगरपालिका "
  },
  {
    "CandidateName": "कृष्ण बहादुर के् सी",
    "Gender": "पुरुष",
    "Age": 67,
    "PartyID": 0,
    "SymbolID": 2522,
    "SymbolName": "गिलास",
    "CandidateID": 340319,
    "StateName": "बागमती प्रदेश",
    "PoliticalPartyName": "राष्ट्रिय जनमोर्चा",
    "ElectionPost": null,
    "DistrictCd": 35,
    "DistrictName": "चितवन",
    "State": 3,
    "SCConstID": "3",
    "CenterConstID": null,
    "SerialNo": 2244,
    "TotalVoteReceived": 12,
    "CastedVote": 0,
    "TotalVoters": 0,
    "Rank": "1",
    "Remarks": null,
    "Samudaya": null,
    "DOB": "2015-05-02",
    "CTZDIST": "बाग्लुङ",
    "FATHER_NAME": "रुद्र बहादुर के् सी",
    "SPOUCE_NAME": "बम कुमारी के् सी",
    "QUALIFICATION": "SLC",
    "EXPERIENCE": "",
    "OTHERDETAILS": "",
    "NAMEOFINST": "",
    "ADDRESS": "चितवन भरतपुर महानगरपालिका ज्यामीरे"
  },
  {
    "CandidateName": "मधु माया अधिकारी",
    "Gender": "महिला",
    "Age": 54,
    "PartyID": 0,
    "SymbolID": 2654,
    "SymbolName": "पानीको जार",
    "CandidateID": 339670,
    "StateName": "बागमती प्रदेश",
    "PoliticalPartyName": "स्वतन्त्र",
    "ElectionPost": null,
    "DistrictCd": 35,
    "DistrictName": "चितवन",
    "State": 3,
    "SCConstID": "3",
    "CenterConstID": null,
    "SerialNo": 2245,
    "TotalVoteReceived": 9,
    "CastedVote": 0,
    "TotalVoters": 0,
    "Rank": "1",
    "Remarks": null,
    "Samudaya": null,
    "DOB": "2028-01-21",
    "CTZDIST": "चितवन",
    "FATHER_NAME": "विष्णु प्रसाद अधिकारी",
    "SPOUCE_NAME": "गोपी लाल देवकोटा",
    "QUALIFICATION": "कक्षा 10",
    "EXPERIENCE": "",
    "OTHERDETAILS": "",
    "NAMEOFINST": "",
    "ADDRESS": "चितवन माडी नगरपालिका "
  },
  {
    "CandidateName": "बिजन गुरुङ",
    "Gender": "पुरुष",
    "Age": 30,
    "PartyID": 0,
    "SymbolID": 2532,
    "SymbolName": "चङ्‌गा",
    "CandidateID": 341673,
    "StateName": "बागमती प्रदेश",
    "PoliticalPartyName": " राष्ट्रिय नागरिक पार्टी",
    "ElectionPost": null,
    "DistrictCd": 35,
    "DistrictName": "चितवन",
    "State": 3,
    "SCConstID": "3",
    "CenterConstID": null,
    "SerialNo": 2246,
    "TotalVoteReceived": 5,
    "CastedVote": 0,
    "TotalVoters": 0,
    "Rank": "1",
    "Remarks": null,
    "Samudaya": null,
    "DOB": "2052-02-12",
    "CTZDIST": "चितवन",
    "FATHER_NAME": "टंक बहादुर  गुरुङ",
    "SPOUCE_NAME": "-",
    "QUALIFICATION": "SLC",
    "EXPERIENCE": "",
    "OTHERDETAILS": "",
    "NAMEOFINST": "",
    "ADDRESS": "चितवन भरतपुर महानगरपालिका रामेशवर"
  },
  {
    "CandidateName": "सेती माया तमाङ",
    "Gender": "महिला",
    "Age": 55,
    "PartyID": 0,
    "SymbolID": 2504,
    "SymbolName": "उडिरहेको माहुरी",
    "CandidateID": 340870,
    "StateName": "बागमती प्रदेश",
    "PoliticalPartyName": "नेशनल रिपब्लिक नेपाल",
    "ElectionPost": null,
    "DistrictCd": 35,
    "DistrictName": "चितवन",
    "State": 3,
    "SCConstID": "3",
    "CenterConstID": null,
    "SerialNo": 2247,
    "TotalVoteReceived": 5,
    "CastedVote": 0,
    "TotalVoters": 0,
    "Rank": "1",
    "Remarks": null,
    "Samudaya": null,
    "DOB": "2027-05-03",
    "CTZDIST": "चितवन",
    "FATHER_NAME": "कृष्णा बहादुर तामाङ",
    "SPOUCE_NAME": "धन सिं तामाङ",
    "QUALIFICATION": "",
    "EXPERIENCE": "",
    "OTHERDETAILS": "",
    "NAMEOFINST": "",
    "ADDRESS": "चितवन भरतपुर महानगरपालिका "
  },
  {
    "CandidateName": "हरि माया  महतो",
    "Gender": "महिला",
    "Age": 36,
    "PartyID": 0,
    "SymbolID": 2531,
    "SymbolName": "चकिया (जाँतो)",
    "CandidateID": 341480,
    "StateName": "बागमती प्रदेश",
    "PoliticalPartyName": "नागरिक उन्मुक्ति पार्टी, नेपाल(एकल चुनाव चिन्ह)",
    "ElectionPost": null,
    "DistrictCd": 35,
    "DistrictName": "चितवन",
    "State": 3,
    "SCConstID": "3",
    "CenterConstID": null,
    "SerialNo": 2248,
    "TotalVoteReceived": 5,
    "CastedVote": 0,
    "TotalVoters": 0,
    "Rank": "1",
    "Remarks": null,
    "Samudaya": null,
    "DOB": "2046-08-03",
    "CTZDIST": "नवलपरासी (बर्दघाट सुस्ता पूर्व)",
    "FATHER_NAME": "रत्‍न बहादुर महतो",
    "SPOUCE_NAME": "वलिराम  महतो",
    "QUALIFICATION": "",
    "EXPERIENCE": "",
    "OTHERDETAILS": "",
    "NAMEOFINST": "",
    "ADDRESS": "चितवन भरतपुर महानगरपालिका "
  },
  {
    "CandidateName": "पार्वती पौडेल(काफ्ले)",
    "Gender": "महिला",
    "Age": 52,
    "PartyID": 0,
    "SymbolID": 2620,
    "SymbolName": "कैंची",
    "CandidateID": 341743,
    "StateName": "बागमती प्रदेश",
    "PoliticalPartyName": "स्वतन्त्र",
    "ElectionPost": null,
    "DistrictCd": 35,
    "DistrictName": "चितवन",
    "State": 3,
    "SCConstID": "3",
    "CenterConstID": null,
    "SerialNo": 2249,
    "TotalVoteReceived": 5,
    "CastedVote": 0,
    "TotalVoters": 0,
    "Rank": "1",
    "Remarks": null,
    "Samudaya": null,
    "DOB": "2029-12-08",
    "CTZDIST": "स्याङजा",
    "FATHER_NAME": "मेघनाथ पौडेल",
    "SPOUCE_NAME": "महदत्त  काफ्ले",
    "QUALIFICATION": "",
    "EXPERIENCE": "",
    "OTHERDETAILS": "",
    "NAMEOFINST": "",
    "ADDRESS": "चितवन माडी नगरपालिका खरकट्टा"
  },
  {
    "CandidateName": "कृष्ण प्रसाद अधिकारी",
    "Gender": "पुरुष",
    "Age": 36,
    "PartyID": 0,
    "SymbolID": 2626,
    "SymbolName": "गमबुट",
    "CandidateID": 340532,
    "StateName": "बागमती प्रदेश",
    "PoliticalPartyName": "स्वतन्त्र",
    "ElectionPost": null,
    "DistrictCd": 35,
    "DistrictName": "चितवन",
    "State": 3,
    "SCConstID": "3",
    "CenterConstID": null,
    "SerialNo": 2250,
    "TotalVoteReceived": 3,
    "CastedVote": 0,
    "TotalVoters": 0,
    "Rank": "1",
    "Remarks": null,
    "Samudaya": null,
    "DOB": "2045-12-11",
    "CTZDIST": "चितवन",
    "FATHER_NAME": "विष्णु प्रसाद अधिकारी",
    "SPOUCE_NAME": "सन्जु  अधिकारी",
    "QUALIFICATION": "+2",
    "EXPERIENCE": "",
    "OTHERDETAILS": "",
    "NAMEOFINST": "",
    "ADDRESS": "चितवन भरतपुर महानगरपालिका वेलहट्टा"
  },
  {
    "CandidateName": "थमन सिग सुनार",
    "Gender": "पुरुष",
    "Age": 38,
    "PartyID": 0,
    "SymbolID": 2542,
    "SymbolName": "ढल्केको छाता",
    "CandidateID": 342135,
    "StateName": "बागमती प्रदेश",
    "PoliticalPartyName": "जनता समाजवादी पार्टी, नेपाल",
    "ElectionPost": null,
    "DistrictCd": 35,
    "DistrictName": "चितवन",
    "State": 3,
    "SCConstID": "3",
    "CenterConstID": null,
    "SerialNo": 2251,
    "TotalVoteReceived": 2,
    "CastedVote": 0,
    "TotalVoters": 0,
    "Rank": "1",
    "Remarks": null,
    "Samudaya": null,
    "DOB": "2044-02-16",
    "CTZDIST": "चितवन",
    "FATHER_NAME": "रख बहादुर सुनार",
    "SPOUCE_NAME": " ",
    "QUALIFICATION": "एस एल सि",
    "EXPERIENCE": "",
    "OTHERDETAILS": "",
    "NAMEOFINST": "",
    "ADDRESS": "चितवन माडी नगरपालिका बगाई"
  },
  {
    "CandidateName": "बद्री लक्ष्मी कवां",
    "Gender": "महिला",
    "Age": 49,
    "PartyID": 0,
    "SymbolID": 2578,
    "SymbolName": "मादल",
    "CandidateID": 339477,
    "StateName": "बागमती प्रदेश",
    "PoliticalPartyName": "नेपाल मजदुर किसान पार्टी",
    "ElectionPost": null,
    "DistrictCd": 35,
    "DistrictName": "चितवन",
    "State": 3,
    "SCConstID": "3",
    "CenterConstID": null,
    "SerialNo": 2252,
    "TotalVoteReceived": 2,
    "CastedVote": 0,
    "TotalVoters": 0,
    "Rank": "1",
    "Remarks": null,
    "Samudaya": null,
    "DOB": "2033-07-14",
    "CTZDIST": "भक्तपुर",
    "FATHER_NAME": "बल राम कवां",
    "SPOUCE_NAME": "राम गोपाल कोजु",
    "QUALIFICATION": "प्रमाण पत्र तह",
    "EXPERIENCE": "",
    "OTHERDETAILS": "",
    "NAMEOFINST": "",
    "ADDRESS": "भक्तपुर भक्तपुर नगरपालिका ब्यासी"
  },
  {
    "CandidateName": "रोल बहादुर गुरुङ्ग",
    "Gender": "पुरुष",
    "Age": 37,
    "PartyID": 0,
    "SymbolID": 2641,
    "SymbolName": "ठेकी",
    "CandidateID": 341286,
    "StateName": "बागमती प्रदेश",
    "PoliticalPartyName": "स्वतन्त्र",
    "ElectionPost": null,
    "DistrictCd": 35,
    "DistrictName": "चितवन",
    "State": 3,
    "SCConstID": "3",
    "CenterConstID": null,
    "SerialNo": 2253,
    "TotalVoteReceived": 1,
    "CastedVote": 0,
    "TotalVoters": 0,
    "Rank": "1",
    "Remarks": null,
    "Samudaya": null,
    "DOB": "2045-05-01",
    "CTZDIST": "चितवन",
    "FATHER_NAME": "काशीराज  गुरुङ्ग",
    "SPOUCE_NAME": "अनिशा  गुरुङ्ग",
    "QUALIFICATION": "",
    "EXPERIENCE": "",
    "OTHERDETAILS": "",
    "NAMEOFINST": "",
    "ADDRESS": "चितवन भरतपुर महानगरपालिका "
  }
]
