[{"CandidateName":"सन्तोष राजवंशी","Gender":"पुरुष","Age":34,"PartyID":0,"SymbolID":2528,"SymbolName":"घण्टी","CandidateID":342293,"StateName":"कोशी प्रदेश","PoliticalPartyName":"राष्ट्रिय स्वतन्त्र पार्टी","ElectionPost":null,"DistrictCd":9,"DistrictName":"मोरङ","State":1,"SCConstID":"4","CenterConstID":null,"SerialNo":255,"TotalVoteReceived":21114,"CastedVote":0,"TotalVoters":0,"Rank":"1","Remarks":null,"Samudaya":null,"DOB":"2048-09-12","CTZDIST":"मोरङ","FATHER_NAME":"राम पुजन राजवंशी","SPOUCE_NAME":"-","QUALIFICATION":"स्‍नातक ","EXPERIENCE":"पत्रकारिता","OTHERDETAILS":"समाज सेवामा समर्पित","NAMEOFINST":"त्रि वि","ADDRESS":"मोरङ विराटनगर महानगरपालिका "},{"CandidateName":"अमन लाल मोदी","Gender":"पुरुष","Age":40,"PartyID":0,"SymbolID":2557,"SymbolName":"पाँचकुने तारा","CandidateID":341465,"StateName":"कोशी प्रदेश","PoliticalPartyName":"नेपाली कम्युनिष्ट पार्टी","ElectionPost":null,"DistrictCd":9,"DistrictName":"मोरङ","State":1,"SCConstID":"4","CenterConstID":null,"SerialNo":256,"TotalVoteReceived":9499,"CastedVote":0,"TotalVoters":0,"Rank":"1","Remarks":null,"Samudaya":null,"DOB":"2042-06-05","CTZDIST":"मोरङ","FATHER_NAME":"पवन लाल मोदी","SPOUCE_NAME":"-","QUALIFICATION":"वि ए स्नातक एम ए ","EXPERIENCE":"प्रतिनिध सभा सदस्यमा निर्वाचित \nमन्त्री (सामान्य प्रशासन)","OTHERDETAILS":"","NAMEOFINST":"त्रि वि","ADDRESS":"मोरङ बुढीगंगा गाउँपालिका तिलाठे"},{"CandidateName":"गुरु राज घिमिरे","Gender":"पुरुष","Age":57,"PartyID":0,"SymbolID":2583,"SymbolName":"रुख","CandidateID":341356,"StateName":"कोशी प्रदेश","PoliticalPartyName":"नेपाली काँग्रेस","ElectionPost":null,"DistrictCd":9,"DistrictName":"मोरङ","State":1,"SCConstID":"4","CenterConstID":null,"SerialNo":257,"TotalVoteReceived":7803,"CastedVote":0,"TotalVoters":0,"Rank":"1","Remarks":null,"Samudaya":null,"DOB":"2025-11-12","CTZDIST":"मोरङ","FATHER_NAME":"हरि प्रसाद घिमिरे","SPOUCE_NAME":"मीरा  लामीछाने (घिमिरे)","QUALIFICATION":"एम ए, विड","EXPERIENCE":"चार पटक लामो राजनीतिक जीवन ७ वटा पुस्तक  प्रकाशन तथा नियमित  ","OTHERDETAILS":"","NAMEOFINST":"टि यु","ADDRESS":"मोरङ ग्रामथान गाउँपालिका झौवाबनी"},{"CandidateName":"जिवन घिमीरे","Gender":"पुरुष","Age":63,"PartyID":0,"SymbolID":2598,"SymbolName":"सुर्य","CandidateID":340158,"StateName":"कोशी प्रदेश","PoliticalPartyName":"नेपाल कम्युनिष्ट पार्टी (एकीकृत मार्क्सवादी लेनिनवादी)","ElectionPost":null,"DistrictCd":9,"DistrictName":"मोरङ","State":1,"SCConstID":"4","CenterConstID":null,"SerialNo":258,"TotalVoteReceived":4520,"CastedVote":0,"TotalVoters":0,"Rank":"1","Remarks":null,"Samudaya":null,"DOB":"2019-10-10","CTZDIST":"मोरङ","FATHER_NAME":"तारा नाथ घिमीरे","SPOUCE_NAME":"विमला  घिमीरे","QUALIFICATION":"स्‍नातक","EXPERIENCE":"मनमोहन विश्वविद्यालयको संस्थापक सह कुलपती\nसामाजिक विकास मन्त्री कोशी प्रदेश सरकार","OTHERDETAILS":"स्वच्छ निष्पक्ष र मर्यादित निर्वाचनमा प्रतिस्पर्धीबाट श्रेष्ठता हासिल गर्ने कार्यमा मेरो प्रतिवद्धता रहने छ।","NAMEOFINST":"","ADDRESS":"मोरङ विराटनगर महानगरपालिका नविन टोल"},{"CandidateName":"कृष्ण कुमार अटल","Gender":"पुरुष","Age":45,"PartyID":0,"SymbolID":2501,"SymbolName":"अँजुलीमा रहेको माटो","CandidateID":341700,"StateName":"कोशी प्रदेश","PoliticalPartyName":"श्रम संस्कृति पार्टी","ElectionPost":null,"DistrictCd":9,"DistrictName":"मोरङ","State":1,"SCConstID":"4","CenterConstID":null,"SerialNo":259,"TotalVoteReceived":701,"CastedVote":0,"TotalVoters":0,"Rank":"1","Remarks":null,"Samudaya":null,"DOB":"2037-09-13","CTZDIST":"सुनसरी","FATHER_NAME":"ओम प्रकाश अटल","SPOUCE_NAME":"गुन्जन  अटल","QUALIFICATION":"१२ कक्षा","EXPERIENCE":"व्यापार,  नोकरी, सामाजिक कार्य","OTHERDETAILS":"","NAMEOFINST":"नेशनल एकेडेमी अफ साइन्स एणड कमर्स","ADDRESS":"मोरङ विराटनगर महानगरपालिका "},{"CandidateName":"माधव प्रसाद आचार्य","Gender":"पुरुष","Age":48,"PartyID":0,"SymbolID":2604,"SymbolName":"हलो","CandidateID":342387,"StateName":"कोशी प्रदेश","PoliticalPartyName":"राष्ट्रिय प्रजातन्त्र पार्टी","ElectionPost":null,"DistrictCd":9,"DistrictName":"मोरङ","State":1,"SCConstID":"4","CenterConstID":null,"SerialNo":260,"TotalVoteReceived":330,"CastedVote":0,"TotalVoters":0,"Rank":"1","Remarks":null,"Samudaya":null,"DOB":"2034-02-22","CTZDIST":"मोरङ","FATHER_NAME":"हरि प्रसाद आचार्य","SPOUCE_NAME":"विन्दा  आचार्य","QUALIFICATION":"वि वि एस","EXPERIENCE":"","OTHERDETAILS":"","NAMEOFINST":"महेन्द्र मोरङ्ग आदर्श बहुमुखी क्याम्पस","ADDRESS":"मोरङ विराटनगर महानगरपालिका कृति मार्ग"},{"CandidateName":"जिवन कुमार गुप्‍ता","Gender":"पुरुष","Age":46,"PartyID":0,"SymbolID":2585,"SymbolName":"लाउड स्पिकर","CandidateID":342472,"StateName":"कोशी प्रदेश","PoliticalPartyName":"जनमत पार्टी","ElectionPost":null,"DistrictCd":9,"DistrictName":"मोरङ","State":1,"SCConstID":"4","CenterConstID":null,"SerialNo":261,"TotalVoteReceived":239,"CastedVote":0,"TotalVoters":0,"Rank":"1","Remarks":null,"Samudaya":null,"DOB":"2036-01-15","CTZDIST":"सप्तरी","FATHER_NAME":"पुस्पेन्द्र कुमार राजेन्द्र,गुप्‍ता","SPOUCE_NAME":"रिकुं  देवी","QUALIFICATION":"slc","EXPERIENCE":"","OTHERDETAILS":"","NAMEOFINST":"","ADDRESS":"मोरङ विराटनगर महानगरपालिका वखरी"},{"CandidateName":"कल्पना देेवि यादव","Gender":"महिला","Age":46,"PartyID":0,"SymbolID":2527,"SymbolName":"गोलो घेराभित्र पानीको बोतल","CandidateID":342132,"StateName":"कोशी प्रदेश","PoliticalPartyName":"राष्ट्र निर्माण दल नेपाल","ElectionPost":null,"DistrictCd":9,"DistrictName":"मोरङ","State":1,"SCConstID":"4","CenterConstID":null,"SerialNo":262,"TotalVoteReceived":135,"CastedVote":0,"TotalVoters":0,"Rank":"1","Remarks":null,"Samudaya":null,"DOB":"2036-01-05","CTZDIST":"सप्तरी","FATHER_NAME":"होमेश्‍वर प्रसाद यादव","SPOUCE_NAME":"सिया राम यादव","QUALIFICATION":"slc","EXPERIENCE":"","OTHERDETAILS":"","NAMEOFINST":"","ADDRESS":"मोरङ विराटनगर महानगरपालिका "},{"CandidateName":"गोल्छा  राई ","Gender":"पुरुष","Age":44,"PartyID":0,"SymbolID":2511,"SymbolName":"कुखुराको भाले","CandidateID":341233,"StateName":"कोशी प्रदेश","PoliticalPartyName":"मंगोल नेशनल अर्गनाइजेसन","ElectionPost":null,"DistrictCd":9,"DistrictName":"मोरङ","State":1,"SCConstID":"4","CenterConstID":null,"SerialNo":263,"TotalVoteReceived":74,"CastedVote":0,"TotalVoters":0,"Rank":"1","Remarks":null,"Samudaya":null,"DOB":"2038-06-13","CTZDIST":"खोटाङ","FATHER_NAME":"पुर्ण  कुमार  राई","SPOUCE_NAME":"सोभा  देवो  राई ","QUALIFICATION":"slc","EXPERIENCE":"श्रम अनि कृषिमा आधारित कठिन वाल्यकालको जिवन देश चिन्ने र विविधता वुझ्ने कठोर भोट प्रदेशको यात्रा अनुशासन र राष्ट्र सेवकको आर्मी जिवन १६ वर्ष २ महिना","OTHERDETAILS":"राजनीति मेरो लागि पद वा सत्ताको साधना होइन यो व्यातिगत आस्था र जिम्मेवारी हो। सहि राजनिति आस्थाले मात्र समाज र देशको उज्जवल भविष्य निर्माण गर्ने भन्न विश्वास राख्दछु।मेरो प्रतिनिधि सभा साझेदारी सत्ता परिवर्तनको लागि मात्र होइन नीतिगत रुपमा आमुल परिवर्तन मार्फत जनताको जिवन स्तर रुपान्तरणको संकल्प हो।","NAMEOFINST":"श्री कालिका वाल विकास मा वी ","ADDRESS":"मोरङ बेलवारी नगरपालिका "},{"CandidateName":"अशोक शर्मा","Gender":"पुरुष","Age":36,"PartyID":0,"SymbolID":2581,"SymbolName":"मोबाइल","CandidateID":342189,"StateName":"कोशी प्रदेश","PoliticalPartyName":"आम जनता पार्टी(एकल चुनाव चिन्ह)","ElectionPost":null,"DistrictCd":9,"DistrictName":"मोरङ","State":1,"SCConstID":"4","CenterConstID":null,"SerialNo":264,"TotalVoteReceived":55,"CastedVote":0,"TotalVoters":0,"Rank":"1","Remarks":null,"Samudaya":null,"DOB":"2046-11-10","CTZDIST":"मोरङ","FATHER_NAME":"मोहन  शर्मा","SPOUCE_NAME":"जमुना देवी शर्मा","QUALIFICATION":"‌+2 ","EXPERIENCE":"फर्निचर व्यवसायी २० वर्षको अनुभव \nनव आदर्श वचत तथा ऋण सहकारीको सचिव\nमोरङ्ग फर्निचर तथा फर्निसिङ्ग जिल्लाको उपाध्यक्ष","OTHERDETAILS":"","NAMEOFINST":"श्री सरस्वती माध्यमिक विद्यालय","ADDRESS":"मोरङ कटहरी गाउँपालिका आदर्शनगर"},{"CandidateName":"हरि बहादुर बस्नेत","Gender":"पुरुष","Age":58,"PartyID":0,"SymbolID":2526,"SymbolName":"गोलो घेराभित्र दुई पात भएको गुलाफको फूल","CandidateID":340292,"StateName":"कोशी प्रदेश","PoliticalPartyName":"नेपाल कम्युनिस्ट पार्टी (माओवादी)","ElectionPost":null,"DistrictCd":9,"DistrictName":"मोरङ","State":1,"SCConstID":"4","CenterConstID":null,"SerialNo":265,"TotalVoteReceived":42,"CastedVote":0,"TotalVoters":0,"Rank":"1","Remarks":null,"Samudaya":null,"DOB":"2024-04-29","CTZDIST":"मोरङ","FATHER_NAME":"यदु कुमार बस्नेत","SPOUCE_NAME":"तारा  बस्नेत","QUALIFICATION":"आइ ए","EXPERIENCE":"धनपाल मा वि व्यवस्थापन अध्यक्ष\nगार्मेन्ट उद्योग बजार व्यवस्थापन\nबेतना तथा लोहन्द्रा नहर सिँचाई संस्थापक अध्यक्ष","OTHERDETAILS":"","NAMEOFINST":"महेन्द्र मोरङ्ग आदर्श बहुमुखी क्याम्पस","ADDRESS":"मोरङ बेलवारी नगरपालिका माथिल्लो कसेनी"},{"CandidateName":"नुमा लिम्बु","Gender":"महिला","Age":39,"PartyID":0,"SymbolID":2590,"SymbolName":"श्रीवत्स समृद्धिको प्रतीक","CandidateID":341068,"StateName":"कोशी प्रदेश","PoliticalPartyName":"समावेशी समाजवादी पार्टी","ElectionPost":null,"DistrictCd":9,"DistrictName":"मोरङ","State":1,"SCConstID":"4","CenterConstID":null,"SerialNo":266,"TotalVoteReceived":41,"CastedVote":0,"TotalVoters":0,"Rank":"1","Remarks":null,"Samudaya":null,"DOB":"2043-04-09","CTZDIST":"झापा","FATHER_NAME":"सिंह बहादुर लिम्बु","SPOUCE_NAME":"-","QUALIFICATION":"प्रविणता प्रमाणपत्र तह","EXPERIENCE":"","OTHERDETAILS":"","NAMEOFINST":"कोशी क्याम्पस विराटनगर","ADDRESS":"झापा दमक नगरपालिका बालुवाटार"},{"CandidateName":"हरि नारायण चौधरी","Gender":"पुरुष","Age":52,"PartyID":0,"SymbolID":2531,"SymbolName":"चकिया (जाँतो)","CandidateID":340858,"StateName":"कोशी प्रदेश","PoliticalPartyName":"नागरिक उन्मुक्ति पार्टी, नेपाल(एकल चुनाव चिन्ह)","ElectionPost":null,"DistrictCd":9,"DistrictName":"मोरङ","State":1,"SCConstID":"4","CenterConstID":null,"SerialNo":267,"TotalVoteReceived":26,"CastedVote":0,"TotalVoters":0,"Rank":"1","Remarks":null,"Samudaya":null,"DOB":"2030-11-07","CTZDIST":"मोरङ","FATHER_NAME":"दुखी  चौधरी","SPOUCE_NAME":"उषा देवी चौधरी","QUALIFICATION":"एस एल सी","EXPERIENCE":"अ हे व मेडिकल \nशिक्षक","OTHERDETAILS":"आफ्नो भाषा संस्कृति रीति रिवाज भेष भुषा सवै जाती वर्ग क्षेेत्र लिङ्गको पहिचान संरक्षण र सम्वर्धन होस् भन्ने चाहना राख्दछु","NAMEOFINST":"प्रगतिशिल मा वि","ADDRESS":"झापा विर्तामोड नगरपालिका सैनिक मोड"},{"CandidateName":"भक्त मणी दाहाल","Gender":"पुरुष","Age":58,"PartyID":0,"SymbolID":2670,"SymbolName":"मुढा","CandidateID":342084,"StateName":"कोशी प्रदेश","PoliticalPartyName":"स्वतन्त्र","ElectionPost":null,"DistrictCd":9,"DistrictName":"मोरङ","State":1,"SCConstID":"4","CenterConstID":null,"SerialNo":268,"TotalVoteReceived":23,"CastedVote":0,"TotalVoters":0,"Rank":"1","Remarks":null,"Samudaya":null,"DOB":"2024-01-07","CTZDIST":"संखुवासभा","FATHER_NAME":"हिरण्य प्रसाद दाहाल","SPOUCE_NAME":"चेतना  अधिकारी","QUALIFICATION":"स्नातकोत्तर","EXPERIENCE":"","OTHERDETAILS":"","NAMEOFINST":"सम्पुर्ण नन्द विश्वविद्यालय","ADDRESS":"मोरङ विराटनगर महानगरपालिका बेलगाछी"},{"CandidateName":"जयराम थारु","Gender":"पुरुष","Age":43,"PartyID":0,"SymbolID":2578,"SymbolName":"मादल","CandidateID":339348,"StateName":"कोशी प्रदेश","PoliticalPartyName":"नेपाल मजदुर किसान पार्टी","ElectionPost":null,"DistrictCd":9,"DistrictName":"मोरङ","State":1,"SCConstID":"4","CenterConstID":null,"SerialNo":269,"TotalVoteReceived":21,"CastedVote":0,"TotalVoters":0,"Rank":"1","Remarks":null,"Samudaya":null,"DOB":"2039-06-13","CTZDIST":"मोरङ","FATHER_NAME":"अन्तराम  थारु","SPOUCE_NAME":"नैनसर  थारु","QUALIFICATION":"साधारण","EXPERIENCE":"","OTHERDETAILS":"नेमकिपाको चुनावी घोषणापत्र अनुसार देश र जनताको हित गर्ने","NAMEOFINST":"","ADDRESS":"मोरङ ग्रामथान गाउँपालिका तेतरीया"},{"CandidateName":"तवरेज अखतर आलम ","Gender":"पुरुष","Age":60,"PartyID":0,"SymbolID":2542,"SymbolName":"ढल्केको छाता","CandidateID":342367,"StateName":"कोशी प्रदेश","PoliticalPartyName":"जनता समाजवादी पार्टी, नेपाल","ElectionPost":null,"DistrictCd":9,"DistrictName":"मोरङ","State":1,"SCConstID":"4","CenterConstID":null,"SerialNo":270,"TotalVoteReceived":19,"CastedVote":0,"TotalVoters":0,"Rank":"1","Remarks":null,"Samudaya":null,"DOB":"2022-07-15","CTZDIST":"मोरङ","FATHER_NAME":"समसाद  आलम","SPOUCE_NAME":"नासिन  खातुन","QUALIFICATION":"slc","EXPERIENCE":"","OTHERDETAILS":"","NAMEOFINST":"","ADDRESS":"मोरङ विराटनगर महानगरपालिका सरौचिया"},{"CandidateName":"ज्ञानेन्द्र खत्री","Gender":"पुरुष","Age":51,"PartyID":0,"SymbolID":2646,"SymbolName":"त्रिभुज","CandidateID":342319,"StateName":"कोशी प्रदेश","PoliticalPartyName":"स्वतन्त्र","ElectionPost":null,"DistrictCd":9,"DistrictName":"मोरङ","State":1,"SCConstID":"4","CenterConstID":null,"SerialNo":271,"TotalVoteReceived":17,"CastedVote":0,"TotalVoters":0,"Rank":"1","Remarks":null,"Samudaya":null,"DOB":"2031-10-08","CTZDIST":"मोरङ","FATHER_NAME":"भुपेन्द्र  खत्री","SPOUCE_NAME":"जमुना कुमारी बस्नेत","QUALIFICATION":"वि ए स्नातक ","EXPERIENCE":"अधिल्लो आम निर्वाचनमा समेत स्वतन्त्र","OTHERDETAILS":"देशको सेवा गर्ने","NAMEOFINST":"त्रि वि","ADDRESS":"मोरङ विराटनगर महानगरपालिका हिमाली टोल"},{"CandidateName":"विनोद कुमार कार्की","Gender":"पुरुष","Age":47,"PartyID":0,"SymbolID":2612,"SymbolName":"आसकोट","CandidateID":342228,"StateName":"कोशी प्रदेश","PoliticalPartyName":"स्वतन्त्र","ElectionPost":null,"DistrictCd":9,"DistrictName":"मोरङ","State":1,"SCConstID":"4","CenterConstID":null,"SerialNo":272,"TotalVoteReceived":11,"CastedVote":0,"TotalVoters":0,"Rank":"1","Remarks":null,"Samudaya":null,"DOB":"2035-02-18","CTZDIST":"मोरङ","FATHER_NAME":"धन बहादुर कार्की","SPOUCE_NAME":"अन्जना  कार्की","QUALIFICATION":"+2 ","EXPERIENCE":"","OTHERDETAILS":"","NAMEOFINST":"","ADDRESS":"मोरङ विराटनगर महानगरपालिका पोखरीया"},{"CandidateName":"हरनु मुसहर","Gender":"पुरुष","Age":67,"PartyID":0,"SymbolID":2550,"SymbolName":"दाप सहितको खुकुरी","CandidateID":342355,"StateName":"कोशी प्रदेश","PoliticalPartyName":"संघीय लोकतान्त्रिक राष्ट्रिय मञ्च","ElectionPost":null,"DistrictCd":9,"DistrictName":"मोरङ","State":1,"SCConstID":"4","CenterConstID":null,"SerialNo":273,"TotalVoteReceived":3,"CastedVote":0,"TotalVoters":0,"Rank":"1","Remarks":null,"Samudaya":null,"DOB":"2015-03-02","CTZDIST":"मोरङ","FATHER_NAME":"मुनेश्‍वर  मुसहर","SPOUCE_NAME":"देवकी  मुसहर","QUALIFICATION":"प्राथमिक तह ","EXPERIENCE":"कृषि पेशा","OTHERDETAILS":"","NAMEOFINST":"","ADDRESS":"मोरङ विराटनगर महानगरपालिका भनपुरा"}]