[{"CandidateName":"सुरेश कुमार चौधरी","Gender":"पुरुष","Age":56,"PartyID":0,"SymbolID":2528,"SymbolName":"घण्टी","CandidateID":341907,"StateName":"लुम्बिनी प्रदेश","PoliticalPartyName":"राष्ट्रिय स्वतन्त्र पार्टी","ElectionPost":null,"DistrictCd":65,"DistrictName":"बाँके","State":5,"SCConstID":"1","CenterConstID":null,"SerialNo":3042,"TotalVoteReceived":24475,"CastedVote":0,"TotalVoters":0,"Rank":"1","Remarks":null,"Samudaya":null,"DOB":"2026-06-16","CTZDIST":"बाँके","FATHER_NAME":"बरु लाल चौधरी","SPOUCE_NAME":"देवी  चौधरी","QUALIFICATION":"","EXPERIENCE":"","OTHERDETAILS":"","NAMEOFINST":"","ADDRESS":"बाँके कोहलपुर नगरपालिका आनन्द नगर"},{"CandidateName":"नारायण प्रसाद गौडेल","Gender":"पुरुष","Age":60,"PartyID":0,"SymbolID":2583,"SymbolName":"रुख","CandidateID":340994,"StateName":"लुम्बिनी प्रदेश","PoliticalPartyName":"नेपाली काँग्रेस","ElectionPost":null,"DistrictCd":65,"DistrictName":"बाँके","State":5,"SCConstID":"1","CenterConstID":null,"SerialNo":3043,"TotalVoteReceived":9543,"CastedVote":0,"TotalVoters":0,"Rank":"1","Remarks":null,"Samudaya":null,"DOB":"2021-12-09","CTZDIST":"कञ्चनपुर","FATHER_NAME":"चन्द्र दत्त गौडेल","SPOUCE_NAME":"कुमारी सिता पोखरेल","QUALIFICATION":"","EXPERIENCE":"","OTHERDETAILS":"","NAMEOFINST":"","ADDRESS":"बाँके कोहलपुर नगरपालिका मदनचोक"},{"CandidateName":"सुर्य प्रसाद ढकाल","Gender":"पुरुष","Age":53,"PartyID":0,"SymbolID":2598,"SymbolName":"सुर्य","CandidateID":339720,"StateName":"लुम्बिनी प्रदेश","PoliticalPartyName":"नेपाल कम्युनिष्ट पार्टी (एकीकृत मार्क्सवादी लेनिनवादी)","ElectionPost":null,"DistrictCd":65,"DistrictName":"बाँके","State":5,"SCConstID":"1","CenterConstID":null,"SerialNo":3044,"TotalVoteReceived":6572,"CastedVote":0,"TotalVoters":0,"Rank":"1","Remarks":null,"Samudaya":null,"DOB":"2029-01-06","CTZDIST":"बाँके","FATHER_NAME":"तुल्सी राम ढकाल","SPOUCE_NAME":"तुसाली  ढकाल","QUALIFICATION":"","EXPERIENCE":"","OTHERDETAILS":"","NAMEOFINST":"","ADDRESS":"बाँके कोहलपुर नगरपालिका चपरगौडी"},{"CandidateName":"नरेन्द्र प्रसाद पाण्डे","Gender":"पुरुष","Age":49,"PartyID":0,"SymbolID":2557,"SymbolName":"पाँचकुने तारा","CandidateID":340433,"StateName":"लुम्बिनी प्रदेश","PoliticalPartyName":"नेपाली कम्युनिष्ट पार्टी","ElectionPost":null,"DistrictCd":65,"DistrictName":"बाँके","State":5,"SCConstID":"1","CenterConstID":null,"SerialNo":3045,"TotalVoteReceived":3083,"CastedVote":0,"TotalVoters":0,"Rank":"1","Remarks":null,"Samudaya":null,"DOB":"2033-10-29","CTZDIST":"कालिकोट","FATHER_NAME":"रत्‍नाखर  पाण्डे","SPOUCE_NAME":"ज्योती  पाण्डे","QUALIFICATION":"","EXPERIENCE":"","OTHERDETAILS":"","NAMEOFINST":"","ADDRESS":"बाँके कोहलपुर नगरपालिका मदन चोक"},{"CandidateName":"प्रदिप कुमार शाह","Gender":"पुरुष","Age":63,"PartyID":0,"SymbolID":2604,"SymbolName":"हलो","CandidateID":340244,"StateName":"लुम्बिनी प्रदेश","PoliticalPartyName":"राष्ट्रिय प्रजातन्त्र पार्टी","ElectionPost":null,"DistrictCd":65,"DistrictName":"बाँके","State":5,"SCConstID":"1","CenterConstID":null,"SerialNo":3046,"TotalVoteReceived":1160,"CastedVote":0,"TotalVoters":0,"Rank":"1","Remarks":null,"Samudaya":null,"DOB":"2019-06-01","CTZDIST":"दाङ","FATHER_NAME":"इन्द्र  शाह","SPOUCE_NAME":"उषा  शाह","QUALIFICATION":"","EXPERIENCE":"","OTHERDETAILS":"","NAMEOFINST":"","ADDRESS":"बाँके कोहलपुर नगरपालिका किरननाला"},{"CandidateName":"कृष्णा के.सी.","Gender":"महिला","Age":46,"PartyID":0,"SymbolID":2516,"SymbolName":"खुलेको एकल आँखा","CandidateID":341346,"StateName":"लुम्बिनी प्रदेश","PoliticalPartyName":"प्रगतिशील लोकतान्त्रिक पार्टी","ElectionPost":null,"DistrictCd":65,"DistrictName":"बाँके","State":5,"SCConstID":"1","CenterConstID":null,"SerialNo":3047,"TotalVoteReceived":364,"CastedVote":0,"TotalVoters":0,"Rank":"1","Remarks":null,"Samudaya":null,"DOB":"2035-12-15","CTZDIST":"बाँके","FATHER_NAME":"चन्द्र बहादुर खत्री","SPOUCE_NAME":"-","QUALIFICATION":"","EXPERIENCE":"","OTHERDETAILS":"","NAMEOFINST":"","ADDRESS":"बाँके राप्तीसोनारी गाउँपालिका ठकेरी उदैन"},{"CandidateName":"भरत निधी तिवारी","Gender":"पुरुष","Age":34,"PartyID":0,"SymbolID":2501,"SymbolName":"अँजुलीमा रहेको माटो","CandidateID":339539,"StateName":"लुम्बिनी प्रदेश","PoliticalPartyName":"श्रम संस्कृति पार्टी","ElectionPost":null,"DistrictCd":65,"DistrictName":"बाँके","State":5,"SCConstID":"1","CenterConstID":null,"SerialNo":3048,"TotalVoteReceived":356,"CastedVote":0,"TotalVoters":0,"Rank":"1","Remarks":null,"Samudaya":null,"DOB":"2048-01-04","CTZDIST":"बाँके","FATHER_NAME":"डम्मर प्रसाद तिवारी","SPOUCE_NAME":"-","QUALIFICATION":"","EXPERIENCE":"","OTHERDETAILS":"","NAMEOFINST":"","ADDRESS":"बाँके कोहलपुर नगरपालिका शान्तीनगर"},{"CandidateName":"धन बहादुर खड्का","Gender":"पुरुष","Age":43,"PartyID":0,"SymbolID":2566,"SymbolName":"बलिरहेको बिजुलीको चिम","CandidateID":341611,"StateName":"लुम्बिनी प्रदेश","PoliticalPartyName":"उज्यालो नेपाल पार्टी","ElectionPost":null,"DistrictCd":65,"DistrictName":"बाँके","State":5,"SCConstID":"1","CenterConstID":null,"SerialNo":3049,"TotalVoteReceived":140,"CastedVote":0,"TotalVoters":0,"Rank":"1","Remarks":null,"Samudaya":null,"DOB":"2039-02-12","CTZDIST":"बाँके","FATHER_NAME":"रुद्र बहादुर खड्का","SPOUCE_NAME":"हरि देवि बुढाथोकी","QUALIFICATION":"","EXPERIENCE":"","OTHERDETAILS":"","NAMEOFINST":"","ADDRESS":"बाँके राप्तीसोनारी गाउँपालिका पेरानी"},{"CandidateName":"दिपक वुढाथोकी","Gender":"पुरुष","Age":29,"PartyID":0,"SymbolID":2526,"SymbolName":"गोलो घेराभित्र दुई पात भएको गुलाफको फूल","CandidateID":340063,"StateName":"लुम्बिनी प्रदेश","PoliticalPartyName":"नेपाल कम्युनिस्ट पार्टी (माओवादी)","ElectionPost":null,"DistrictCd":65,"DistrictName":"बाँके","State":5,"SCConstID":"1","CenterConstID":null,"SerialNo":3050,"TotalVoteReceived":102,"CastedVote":0,"TotalVoters":0,"Rank":"1","Remarks":null,"Samudaya":null,"DOB":"2052-12-19","CTZDIST":"सल्यान","FATHER_NAME":"विर बहादुर बुढाथोकी","SPOUCE_NAME":"-","QUALIFICATION":"","EXPERIENCE":"","OTHERDETAILS":"","NAMEOFINST":"","ADDRESS":"सल्यान कुमाख गाउँपालिका रुमालगाउँ"},{"CandidateName":"तुलसी राम सापकोटा","Gender":"पुरुष","Age":68,"PartyID":0,"SymbolID":2522,"SymbolName":"गिलास","CandidateID":339516,"StateName":"लुम्बिनी प्रदेश","PoliticalPartyName":"राष्ट्रिय जनमोर्चा","ElectionPost":null,"DistrictCd":65,"DistrictName":"बाँके","State":5,"SCConstID":"1","CenterConstID":null,"SerialNo":3051,"TotalVoteReceived":94,"CastedVote":0,"TotalVoters":0,"Rank":"1","Remarks":null,"Samudaya":null,"DOB":"2014-07-16","CTZDIST":"रूपन्देही","FATHER_NAME":"देवपति  सापकोटा","SPOUCE_NAME":"याम कला सापकोटा","QUALIFICATION":"","EXPERIENCE":"","OTHERDETAILS":"","NAMEOFINST":"","ADDRESS":"बाँके कोहलपुर नगरपालिका "},{"CandidateName":"सुर्जा थापा","Gender":"महिला","Age":40,"PartyID":0,"SymbolID":2578,"SymbolName":"मादल","CandidateID":339471,"StateName":"लुम्बिनी प्रदेश","PoliticalPartyName":"नेपाल मजदुर किसान पार्टी","ElectionPost":null,"DistrictCd":65,"DistrictName":"बाँके","State":5,"SCConstID":"1","CenterConstID":null,"SerialNo":3052,"TotalVoteReceived":47,"CastedVote":0,"TotalVoters":0,"Rank":"1","Remarks":null,"Samudaya":null,"DOB":"2042-01-10","CTZDIST":"दैलेख","FATHER_NAME":"रण बहादुर रोकाय","SPOUCE_NAME":"खडग राज थापा","QUALIFICATION":"","EXPERIENCE":"","OTHERDETAILS":"","NAMEOFINST":"","ADDRESS":"बाँके कोहलपुर नगरपालिका "},{"CandidateName":"राजेन्द्र कुमार विश्वकर्मा","Gender":"पुरुष","Age":45,"PartyID":0,"SymbolID":2542,"SymbolName":"ढल्केको छाता","CandidateID":342543,"StateName":"लुम्बिनी प्रदेश","PoliticalPartyName":"जनता समाजवादी पार्टी, नेपाल","ElectionPost":null,"DistrictCd":65,"DistrictName":"बाँके","State":5,"SCConstID":"1","CenterConstID":null,"SerialNo":3053,"TotalVoteReceived":37,"CastedVote":0,"TotalVoters":0,"Rank":"1","Remarks":null,"Samudaya":null,"DOB":"2037-04-10","CTZDIST":"बाँके","FATHER_NAME":"सन्त राम विश्वकर्मा","SPOUCE_NAME":"लक्ष्मी  शर्मा","QUALIFICATION":"","EXPERIENCE":"","OTHERDETAILS":"","NAMEOFINST":"","ADDRESS":"बाँके नरैनापुर गाउँपालिका भोजपुर"},{"CandidateName":"दिवाकर​ शर्मा","Gender":"पुरुष","Age":39,"PartyID":0,"SymbolID":2670,"SymbolName":"मुढा","CandidateID":341420,"StateName":"लुम्बिनी प्रदेश","PoliticalPartyName":"स्वतन्त्र","ElectionPost":null,"DistrictCd":65,"DistrictName":"बाँके","State":5,"SCConstID":"1","CenterConstID":null,"SerialNo":3054,"TotalVoteReceived":24,"CastedVote":0,"TotalVoters":0,"Rank":"1","Remarks":null,"Samudaya":null,"DOB":"2043-08-10","CTZDIST":"सुर्खेत","FATHER_NAME":"चन्द्र​ प्रसाद​ जैसी","SPOUCE_NAME":"-","QUALIFICATION":"","EXPERIENCE":"","OTHERDETAILS":"","NAMEOFINST":"","ADDRESS":"बाँके कोहलपुर नगरपालिका "},{"CandidateName":"फेरुलाल चौधरी","Gender":"पुरुष","Age":48,"PartyID":0,"SymbolID":2511,"SymbolName":"कुखुराको भाले","CandidateID":339966,"StateName":"लुम्बिनी प्रदेश","PoliticalPartyName":"मंगोल नेशनल अर्गनाइजेसन","ElectionPost":null,"DistrictCd":65,"DistrictName":"बाँके","State":5,"SCConstID":"1","CenterConstID":null,"SerialNo":3055,"TotalVoteReceived":8,"CastedVote":0,"TotalVoters":0,"Rank":"1","Remarks":null,"Samudaya":null,"DOB":"2034-01-05","CTZDIST":"दाङ","FATHER_NAME":"फकिरु  चौधरी","SPOUCE_NAME":"सिता कुमारी चौधरी","QUALIFICATION":"","EXPERIENCE":"","OTHERDETAILS":"","NAMEOFINST":"","ADDRESS":"दाङ राप्ती गाउँपालिका "}]